common/__init__.py
common/aws_/__init__.py
common/b64uuid_/__init__.py
common/compress_/__init__.py
common/compress_/gzip_.py
common/compress_/lzma_.py
common/compress_/zlib_.py
common/cryptography_/__init__.py
common/json_/__init__.py
common/requests_/__init__.py
common/times_/__init__.py
dfmodule-0.0.8.dist-info/METADATA
dfmodule-0.0.8.dist-info/WHEEL
dfmodule-0.0.8.dist-info/top_level.txt
dfmodule-0.0.8.dist-info/RECORD
