Metadata-Version: 2.1
Name: dfmodule
Version: 0.0.8
Summary: data management project common features module
Home-page: 
Author: rimmoyee
Author-email: rimmoyee@gmail.com
Keywords: dfmodule,dfmodule777
Classifier: Programming Language :: Python :: 3.6
Classifier: Programming Language :: Python :: 3.7
Classifier: Programming Language :: Python :: 3.8
Classifier: Programming Language :: Python :: 3.9
Classifier: Programming Language :: Python :: 3.10
Requires-Python: >=3.6
Requires-Dist: boto3
Requires-Dist: b64uuid
Requires-Dist: cryptography
Requires-Dist: requests
